LICENSE
MANIFEST.in
README.md
setup.cfg
setup.py
modular_mujoco_envs/__init__.py
modular_mujoco_envs/modular_half_cheetah_env.py
modular_mujoco_envs/modular_hopper_env.py
modular_mujoco_envs/modular_humanoid2d_env.py
modular_mujoco_envs/modular_mujoco_env.py
modular_mujoco_envs/modular_walker2d_env.py
modular_mujoco_envs/utils.py
modular_mujoco_envs.egg-info/PKG-INFO
modular_mujoco_envs.egg-info/SOURCES.txt
modular_mujoco_envs.egg-info/dependency_links.txt
modular_mujoco_envs.egg-info/top_level.txt
modular_mujoco_envs/misc/materials.xml
modular_mujoco_envs/misc/materials_white.xml
modular_mujoco_envs/misc/skybox.xml
modular_mujoco_envs/misc/skybox_white.xml
modular_mujoco_envs/misc/visual.xml
modular_mujoco_envs/misc/visual_copy.xml
modular_mujoco_envs/misc/visual_white.xml
modular_mujoco_envs/xmls/cheetah_2_back.xml
modular_mujoco_envs/xmls/cheetah_2_front.xml
modular_mujoco_envs/xmls/cheetah_3_back.xml
modular_mujoco_envs/xmls/cheetah_3_balanced.xml
modular_mujoco_envs/xmls/cheetah_3_front.xml
modular_mujoco_envs/xmls/cheetah_4_allback.xml
modular_mujoco_envs/xmls/cheetah_4_allfront.xml
modular_mujoco_envs/xmls/cheetah_4_back.xml
modular_mujoco_envs/xmls/cheetah_4_front.xml
modular_mujoco_envs/xmls/cheetah_5_back.xml
modular_mujoco_envs/xmls/cheetah_5_balanced.xml
modular_mujoco_envs/xmls/cheetah_5_front.xml
modular_mujoco_envs/xmls/cheetah_6_back.xml
modular_mujoco_envs/xmls/cheetah_6_front.xml
modular_mujoco_envs/xmls/cheetah_7_full.xml
modular_mujoco_envs/xmls/hopper_3.xml
modular_mujoco_envs/xmls/hopper_4.xml
modular_mujoco_envs/xmls/hopper_5.xml
modular_mujoco_envs/xmls/humanoid_2d_7_left_arm.xml
modular_mujoco_envs/xmls/humanoid_2d_7_left_leg.xml
modular_mujoco_envs/xmls/humanoid_2d_7_lower_arms.xml
modular_mujoco_envs/xmls/humanoid_2d_7_right_arm.xml
modular_mujoco_envs/xmls/humanoid_2d_7_right_leg.xml
modular_mujoco_envs/xmls/humanoid_2d_8_left_knee.xml
modular_mujoco_envs/xmls/humanoid_2d_8_right_knee.xml
modular_mujoco_envs/xmls/humanoid_2d_9_full.xml
modular_mujoco_envs/xmls/walker_2_flipped.xml
modular_mujoco_envs/xmls/walker_2_main.xml
modular_mujoco_envs/xmls/walker_3_flipped.xml
